stex_client/__init__.py
stex_client/constant.py
stex_client/private.py
stex_client/public.py
stex_client/websocket.py
stex_client/wss.py
stex_client-1.0.5.dist-info/METADATA
stex_client-1.0.5.dist-info/RECORD
stex_client-1.0.5.dist-info/WHEEL
stex_client-1.0.5.dist-info/top_level.txt
