Metadata-Version: 2.1
Name: stex-client
Version: 1.0.5
Summary: Stex API V3 client for python.
Home-page: https://github.com/StocksExchange/python_client
Author: STEX (Stocks.Exchange)
Author-email: analytics@stex.com
License: MIT
Keywords: api client request stocks.exchange stex library websocket-client stex.com
Platform: UNKNOWN
Classifier: License :: OSI Approved :: MIT License
Classifier: Programming Language :: Python :: 3.5
Classifier: Programming Language :: Python :: 3.6
Requires-Python: >=3.5
Requires-Dist: requests
Requires-Dist: furl
Requires-Dist: pendulum
Requires-Dist: python-socketio
